geo_street_talk
