Metadata-Version: 1.0
Name: geo-street-talk
Version: 0.1.2.2
Summary: Geo-street-talk
Home-page: https://github.com/Streets-Data-Collaborative/geo-street-talk-global
Author: Yukun Wan
Author-email: yw3447@nyu.edu
License: MIT
Platform: UNKNOWN
